odoo8_addon_l10n_ar_sale_order-8.0.1.0.0-py2.7-nspkg.pth
odoo_addons/l10n_ar_sale_order/.gitignore
odoo_addons/l10n_ar_sale_order/README.md
odoo_addons/l10n_ar_sale_order/__openerp__.py
odoo_addons/l10n_ar_sale_order/sale.py
odoo_addons/l10n_ar_sale_order/sale_view.xml
odoo_addons/l10n_ar_sale_order/__init__.py
odoo8_addon_l10n_ar_sale_order-8.0.1.0.0.dist-info/top_level.txt
odoo8_addon_l10n_ar_sale_order-8.0.1.0.0.dist-info/WHEEL
odoo8_addon_l10n_ar_sale_order-8.0.1.0.0.dist-info/RECORD
odoo8_addon_l10n_ar_sale_order-8.0.1.0.0.dist-info/metadata.json
odoo8_addon_l10n_ar_sale_order-8.0.1.0.0.dist-info/DESCRIPTION.rst
odoo8_addon_l10n_ar_sale_order-8.0.1.0.0.dist-info/METADATA
odoo8_addon_l10n_ar_sale_order-8.0.1.0.0.dist-info/namespace_packages.txt
