Metadata-Version: 2.0
Name: odoo8-addon-l10n-ar-sale-order
Version: 8.0.1.0.0
Summary: Sale Order interactive
Home-page: http://e-mips.com.ar
Author: UNKNOWN
Author-email: UNKNOWN
License: GPL-3
Platform: UNKNOWN
Requires-Dist: odoo (<9.0a,>=8.0a)
Classifier: Programming Language :: Python :: 2.7
Classifier: Framework :: Odoo
Classifier: License :: OSI Approved :: GNU General Public License v3 (GPLv3)
